{
  "project_info": {
    "project_number": "846439380028",
    "project_id": "ezpark-auth-4ca3e",
    "storage_bucket": "ezpark-auth-4ca3e.appspot.com"
  },
  "client": [
    {
      "client_info": {
        "mobilesdk_app_id": "1:846439380028:android:2309ce826b59a2af6d3f39",
        "android_client_info": {
          "package_name": "com.ezpark"
        }
      },
      "oauth_client": [
        {
          "client_id": "846439380028-jj1eirne103fl3n5dmuo02m23ma1f30i.apps.googleusercontent.com",
          "client_type": 3
        }
      ],
      "api_key": [
        {
          "current_key": "AIzaSyCYciRolf7wRjfQln989Tk4REwSeZl0zlE"
        }
      ],
      "services": {
        "appinvite_service": {
          "other_platform_oauth_client": [
            {
              "client_id": "846439380028-jj1eirne103fl3n5dmuo02m23ma1f30i.apps.googleusercontent.com",
              "client_type": 3
            }
          ]
        }
      }
    }
  ],
  "configuration_version": "1"
}